fasting/__init__.py
fasting/cli.py
fasting/fasting.py
fasting/quantify.py
fasting-0.1.0.dist-info/AUTHORS.rst
fasting-0.1.0.dist-info/LICENSE
fasting-0.1.0.dist-info/METADATA
fasting-0.1.0.dist-info/WHEEL
fasting-0.1.0.dist-info/dependency_links.txt
fasting-0.1.0.dist-info/entry_points.txt
fasting-0.1.0.dist-info/top_level.txt
fasting-0.1.0.dist-info/RECORD
