Metadata-Version: 2.1
Name: fasting
Version: 0.1.0
Summary: A Python package to  interact with fasting logs from apps like Zero.
Home-page: https://github.com/jbpauly/fasting
Author: Joe Pauly
Author-email: joseph.b.pauly@gmail.com
License: MIT license
Keywords: fasting
Platform: UNKNOWN
Classifier: Development Status :: 2 - Pre-Alpha
Classifier: Intended Audience :: Developers
Classifier: License :: OSI Approved :: MIT License
Classifier: Natural Language :: English
Classifier: Programming Language :: Python :: 3
Classifier: Programming Language :: Python :: 3.7
Classifier: Programming Language :: Python :: 3.8
Requires-Python: >=3.7
Requires-Dist: pandas (==1.2.*)
